{
    "Author": "rail",
    "Name": "Aetherial Arena",
    "Punchline": "Find and collect creatures to fight.",
    "Description": "Open with /aarena. Search and discover more creatures around the world.",
    "Changelog": "v0.2.0.0: Sprites 90% complete, added aether stamina and regen, collection window, capture system.",
    "IsHide": false,
    "InternalName": "AetherialArena",
    "AssemblyVersion": "0.2.0.0",
    "TestingAssemblyVersion": "0.2.0.0",
    "IsTestingExclusive": false,
    "RepoUrl": "https://github.com/rail2025/AetherialArena",
    "ApplicableVersion": "any",
    "Tags": [
        "find",
        "collect",
        "fight"
    ],
    "DalamudApiLevel": 12,
    "TestingDalamudApiLevel": 12,
    "DownloadLinkInstall": "https://github.com/rail2025/AetherBreaker/releases/download/v0.2.0.0/latest.zip",
    "DownloadLinkUpdate": "https://github.com/rail2025/AetherBreaker/releases/download/v0.2.0.0/latest.zip",
    "DownloadLinkTesting": "https://github.com/rail2025/AetherBreaker/releases/download/v0.2.0.0/latest.zip",
    "LoadPriority": 0,
    "SupportsProfiles": true,
    "IconUrl": "https://raw.githubusercontent.com/rail2025/AetherialArena/refs/heads/master/icon.png"
}

